README.rst
setup.py
globussh/__init__.py
globussh/core.py
globussh.egg-info/PKG-INFO
globussh.egg-info/SOURCES.txt
globussh.egg-info/dependency_links.txt
globussh.egg-info/pbr.json
globussh.egg-info/top_level.txt
globussh.egg-info/zip-safe