Metadata-Version: 1.0
Name: globussh
Version: 0.1.2
Summary: Globus CLI bindings
Home-page: http://github.com/maxhutch/globussh/
Author: Max Hutchinson
Author-email: maxhutch@gmail.com
License: MIT
Keywords: globus
Platform: UNKNOWN
